django_opentelemetry/__init__.py
django_opentelemetry/_compat.py
django_opentelemetry/apps.py
django_opentelemetry/features.py
django_opentelemetry/model_signals.py
django_opentelemetry/task_signals.py
django_opentelemetry/contrib/__init__.py
django_opentelemetry/contrib/channels/__init__.py
django_opentelemetry/contrib/channels/middleware.py
django_opentelemetry-0.0.3.dist-info/METADATA
django_opentelemetry-0.0.3.dist-info/WHEEL
django_opentelemetry-0.0.3.dist-info/licenses/LICENSE.txt
django_opentelemetry-0.0.3.dist-info/RECORD
